web_ext_helper/classes.py
web_ext_helper/functions.py
web_ext_helper/web_ext_helper.py
web_ext_helper-1.2.4.dist-info/entry_points.txt
web_ext_helper-1.2.4.dist-info/LICENSE
web_ext_helper-1.2.4.dist-info/METADATA
web_ext_helper-1.2.4.dist-info/WHEEL
web_ext_helper-1.2.4.dist-info/RECORD
