Metadata-Version: 2.3
Name: web-ext-helper
Version: 1.2.4
Summary: An awesome CLI for building, publishing and running web extensions.
License: GPL-3.0-or-later
Author: AppSolves
Author-email: appsolves@gmail.com
Requires-Python: >=3.11,<4.0
Classifier: License :: OSI Approved :: GNU General Public License v3 or later (GPLv3+)
Classifier: Programming Language :: Python :: 3
Classifier: Programming Language :: Python :: 3.11
Classifier: Programming Language :: Python :: 3.12
Classifier: Programming Language :: Python :: 3.13
Requires-Dist: appdirs (>=1.4.4,<2.0.0)
Requires-Dist: pyjwt (>=2.7.0,<3.0.0)
Requires-Dist: python-dotenv (>=1.0.0,<2.0.0)
Requires-Dist: rich
